common_catalog/__init__.py
common_catalog/apps.py
common_catalog/cms_apps.py
common_catalog/cms_plugins.py
common_catalog/cms_toolbars.py
common_catalog/constants.py
common_catalog/urls.py
common_catalog/utils.py
common_catalog/views.py
common_catalog/admin/__init__.py
common_catalog/admin/fields.py
common_catalog/admin/forms.py
common_catalog/admin/mixins.py
common_catalog/admin/options.py
common_catalog/admin/translatable_entangled.py
common_catalog/locale/cs/LC_MESSAGES/django.mo
common_catalog/locale/cs/LC_MESSAGES/django.po
common_catalog/management/__init__.py
common_catalog/management/commands/__init__.py
common_catalog/management/commands/common_catalog_upgrade_attributes.py
common_catalog/migrations/0001_initial.py
common_catalog/migrations/0002_add_attribute_position.py
common_catalog/migrations/__init__.py
common_catalog/models/__init__.py
common_catalog/models/catalog.py
common_catalog/models/mixins.py
common_catalog/models/plugins.py
common_catalog/templates/common_catalog/catalogitem_detail.html
common_catalog/templates/common_catalog/catalogitem_list.html
common_catalog/templates/common_catalog/pagination.html
common_catalog/templates/common_catalog/plugins/filter.html
common_catalog/templates/common_catalog/plugins/filter_type.html
common_catalog/templates/common_catalog/plugins/filtered_items_list.html
common_catalog/templates/common_catalog/plugins/filtered_items_number.html
common_catalog/templatetags/__init__.py
common_catalog/templatetags/common_catalog.py
djangocms_common_catalog-2.1.3.dist-info/METADATA
djangocms_common_catalog-2.1.3.dist-info/WHEEL
djangocms_common_catalog-2.1.3.dist-info/top_level.txt
djangocms_common_catalog-2.1.3.dist-info/RECORD
