Metadata-Version: 2.4
Name: djangocms-common-catalog
Version: 2.1.3
Summary: DjangoCMS Common Catalog
Home-page: https://gitlab.nic.cz/djangocms-apps/djangocms-common-catalog.git
Author: Zdeněk Böhm, CZ.NIC
Author-email: zdenek.bohm@nic.cz
License: GPLv3+
Platform: posix
Classifier: Typing :: Typed
Classifier: Programming Language :: Python
Classifier: Programming Language :: Python :: 3.10
Classifier: Programming Language :: Python :: 3.11
Classifier: Programming Language :: Python :: 3.12
Classifier: Framework :: Django CMS :: 4.1
Classifier: Framework :: Django CMS :: 5.0
Requires-Python: >=3.10
Requires-Dist: django-cms<6,>=4.1
Requires-Dist: djangocms-text~=0.9
Requires-Dist: django-filer~=3.3
Requires-Dist: django-parler>=1.9.2
Requires-Dist: djangocms-attributes-field>=3.0
Requires-Dist: django-entangled~=0.7
Provides-Extra: quality
Requires-Dist: flake8; extra == "quality"
Requires-Dist: isort; extra == "quality"
Requires-Dist: mypy; extra == "quality"
Requires-Dist: polint; extra == "quality"
Requires-Dist: pydocstyle; extra == "quality"
